{"name": "ifortuna_cz_14582", "sources": [{"web": "http://ifortuna.cz", "name": "Fortuna"}], "identifier": "14582", "title": "Politika | \u010cesko-komun\u00e1ln\u00ed volby 2018-Hlavn\u00ed m\u011bsto Praha - odds from ifortuna.cz", "language": "en", "profile": "data-package", "description": "Scraped odds from ifortuna.cz for: Politika | \u010cesko-komun\u00e1ln\u00ed volby 2018-Hlavn\u00ed m\u011bsto Praha; Zastupitelstva obc\u00ed a m\u011bst (Celkov\u00e9 um\u00edst\u011bn\u00ed)", "resources": [{"langugage": "cs", "name": "odds", "schema": {"fields": [{"format": "YYYY-mm-ddTHH:ii:ss.uuuuuu", "name": "date", "description": "Date and time (UTC) of retrieving the information", "type": "date"}, {"name": "title", "description": "Title of the bet/race", "type": "string"}, {"name": "result", "description": "Result, which can be bet on", "type": "string"}, {"name": "odds", "description": "Odds for the result", "type": "number"}, {"format": "j.n. HH:ii", "name": "date_bet", "description": "Date of the bet/race", "type": "date"}, {"name": "identifier", "description": "Identifier from ifortuna.cz", "type": "integer"}]}, "path": "odds.csv"}]}