{"resources": [{"schema": {"fields": [{"format": "YYYY-mm-ddTHH:ii:ss.uuuuuu", "description": "Date and time (UTC) of retrieving the information", "type": "date", "name": "date"}, {"description": "Title of the bet/race", "type": "string", "name": "title"}, {"description": "Result, which can be bet on", "type": "string", "name": "result"}, {"description": "Odds for the result", "type": "number", "name": "odds"}, {"format": "j.n. HH:ii", "description": "Date of the bet/race", "type": "date", "name": "date_bet"}, {"description": "Identifier from ifortuna.cz", "type": "integer", "name": "identifier"}]}, "path": "odds.csv", "langugage": "cs", "name": "odds"}], "name": "ifortuna_cz_10591", "title": "Politika | Prvn\u00ed prim\u00e1tor hl.m. Prahy - odds from ifortuna.cz", "identifier": "10591", "language": "en", "description": "Scraped odds from ifortuna.cz for: Politika | Prvn\u00ed prim\u00e1tor hl.m. Prahy (V\u00edt\u011bz)", "sources": [{"web": "http://ifortuna.cz", "name": "Fortuna"}]}